cpp/__init__.py
cpp/bits_stdcpp_h.py
cpp/cpp_array.py
cpp/cstdio.py
cpp/iostream.py
cpp/multi_array.py
cpp/pointer.py
cpp/queue.py
cpp/stack.py
cpp/string.py
cpp/vector.py
cpp_py_sqm-0.1.1.dist-info/licenses/license
cpp_py_sqm-0.1.1.dist-info/METADATA
cpp_py_sqm-0.1.1.dist-info/WHEEL
cpp_py_sqm-0.1.1.dist-info/top_level.txt
cpp_py_sqm-0.1.1.dist-info/RECORD
