Metadata-Version: 2.4
Name: cpp_py_sqm
Version: 0.1.1
Summary: A C++-style simulation library for Python（模拟C++风格的Python工具库）
Author: sqm
Author-email: shiqianmo@126.com
Classifier: Programming Language :: Python :: 3
Classifier: License :: OSI Approved :: MIT License
Classifier: Operating System :: OS Independent
Classifier: Intended Audience :: Developers
Classifier: Topic :: Software Development :: Libraries :: Python Modules
Requires-Python: >=3.6
License-File: license
Dynamic: author
Dynamic: author-email
Dynamic: classifier
Dynamic: description
Dynamic: description-content-type
Dynamic: license-file
Dynamic: requires-python
Dynamic: summary
